INSTALL.txt
LICENSE.txt
MANIFEST.in
README.txt
setup.py
grammy/__init__.py
grammy/gemaux.py
grammy/gemcore.cpp
grammy/gemcore.hpp
grammy/gemcore.py
grammy/gemcore_wrap.cpp
grammy/gemlib.py
grammy/gemmath.py
grammy/gemutil.py
grammy/kmercore.cpp
grammy/kmercore.hpp
grammy/mmio.c
grammy/mmio.h
grammy/mydebug.cpp
grammy/mydebug.hpp
grammy.egg-info/PKG-INFO
grammy.egg-info/SOURCES.txt
grammy.egg-info/dependency_links.txt
grammy.egg-info/not-zip-safe
grammy.egg-info/requires.txt
grammy.egg-info/top_level.txt
scripts/grammy-em.py
scripts/grammy-gdt.py
scripts/grammy-post.py
scripts/grammy-pre.py
scripts/grammy-rdt.py