Metadata-Version: 1.1
Name: grammy
Version: 1.0.0
Summary: GRAMMY GENOME Relative Abundance based on Mixture Model theorY.
Home-page: http://meta.usc.edu/softs/grammy
Author: Li Charlie Xia
Author-email: lxia@usc.edu
License: BSD
Keywords: python,grammy,EM,Mixture Models
Platform: Linux
Classifier: Development Status :: 5 - Production/Stable
Classifier: Environment :: Console
Classifier: License :: OSI Approved :: BSD License
Classifier: Programming Language :: Python
Classifier: Programming Language :: C++
Provides: grammy
